decimal_sdk/__init__.py
decimal_sdk/api.py
decimal_sdk/check.py
decimal_sdk/methods.py
decimal_sdk/transactions.py
decimal_sdk/tx_types.py
decimal_sdk/types.py
decimal_sdk/wallet.py
decimal_sdk/msgs/__init__.py
decimal_sdk/msgs/base.py
decimal_sdk/msgs/msgs.py
decimal_sdk/utils/__init__.py
decimal_sdk/utils/fields_validator.py
decimal_sdk/utils/helpers.py
decimal_python_sdk-0.2.1.dist-info/LICENCE
decimal_python_sdk-0.2.1.dist-info/METADATA
decimal_python_sdk-0.2.1.dist-info/WHEEL
decimal_python_sdk-0.2.1.dist-info/top_level.txt
decimal_python_sdk-0.2.1.dist-info/RECORD
