Metadata-Version: 2.1
Name: decimal-python-sdk
Version: 0.2.1
Home-page: https://bitbucket.org/decimalteam/decimal-python-sdk
Author: DecimalTeam
Classifier: Programming Language :: Python :: 3
Classifier: License :: OSI Approved :: MIT License
Classifier: Operating System :: OS Independent
Requires-Python: >=3.6
License-File: LICENCE
Requires-Dist: PyYAML (==5.4.1)
Requires-Dist: asn1crypto (==1.4.0)
Requires-Dist: base58 (==2.0.0)
Requires-Dist: base58check (==1.0.2)
Requires-Dist: bech32 (==1.2.0)
Requires-Dist: bip32 (==0.0.8)
Requires-Dist: cached-property (==1.5.2)
Requires-Dist: certifi (==2020.11.8)
Requires-Dist: cffi (==1.14.3)
Requires-Dist: chardet (==3.0.4)
Requires-Dist: coincurve (==13.0.0)
Requires-Dist: cytoolz (==0.11.0)
Requires-Dist: ecdsa (==0.16.1)
Requires-Dist: eth-hash (==0.3.1)
Requires-Dist: eth-typing (==2.2.2)
Requires-Dist: eth-utils (==1.10.0)
Requires-Dist: ethereum (==2.3.2)
Requires-Dist: future (==0.18.2)
Requires-Dist: idna (==2.10)
Requires-Dist: mnemonic (==0.19)
Requires-Dist: mypy-extensions (==0.4.3)
Requires-Dist: pbkdf2 (==1.3)
Requires-Dist: py-ecc (==5.1.0)
Requires-Dist: pyaes (==1.6.1)
Requires-Dist: pycparser (==2.20)
Requires-Dist: pycryptodome (==3.9.9)
Requires-Dist: pycryptodomex (==3.9.9)
Requires-Dist: pyethash (==0.1.27)
Requires-Dist: pysha3 (==1.0.2)
Requires-Dist: repoze.lru (==0.7)
Requires-Dist: requests (==2.25.0)
Requires-Dist: rlp (==1.2.0)
Requires-Dist: rpl (==1.8.1)
Requires-Dist: scrypt (==0.8.17)
Requires-Dist: six (==1.15.0)
Requires-Dist: sslcrypto (==2.0)
Requires-Dist: toolz (==0.11.1)
Requires-Dist: urllib3 (==1.26.2)
